tabulate/__init__.py
tabulate/version.py
tabulated-0.10.0.dist-info/LICENSE
tabulated-0.10.0.dist-info/METADATA
tabulated-0.10.0.dist-info/WHEEL
tabulated-0.10.0.dist-info/entry_points.txt
tabulated-0.10.0.dist-info/top_level.txt
tabulated-0.10.0.dist-info/RECORD
