Metadata-Version: 2.1
Name: tabulated
Version: 0.10.0
Summary: Pretty-print tabular data, fork of original tabulate.
Author-email: Sergey Astanin <s.astanin@gmail.com>
License: MIT
Project-URL: Homepage, https://github.com/kotborealis/python-tabulated
Classifier: Development Status :: 4 - Beta
Classifier: License :: OSI Approved :: MIT License
Classifier: Operating System :: OS Independent
Classifier: Programming Language :: Python :: 3
Classifier: Programming Language :: Python :: 3.7
Classifier: Programming Language :: Python :: 3.8
Classifier: Programming Language :: Python :: 3.9
Classifier: Programming Language :: Python :: 3.10
Classifier: Programming Language :: Python :: 3.11
Classifier: Topic :: Software Development :: Libraries
Requires-Python: >=3.7
License-File: LICENSE
Provides-Extra: widechars
Requires-Dist: wcwidth ; extra == 'widechars'
